{"intents": [
        {"tag": "greeting",
         "patterns": ["Hi", "How are you", "Is anyone there?", "Hello"],
         "responses": ["Hello, there.", "Hi, how can I help?"]
        },
        {"tag": "spelling",
         "patterns": ["How to spell", "Why does it sound like this", "What to ", "Hello"],
         "responses": ["Let's get it started."]
        },
        {"tag": "ready",
         "patterns": ["Ready", "Start", "Please begin", "I am ready"],
         "responses": ["Just say Study "]
        },
        {"tag": "goodbye",
         "patterns": ["Bye", "See you later", "Goodbye"],
         "responses": ["See you later!", "Have a nice day", "Bye! Come back again soon."]
        },
        {"tag": "thanks",
         "patterns": ["Thanks", "Thank you", "That's helpful"],
         "responses": ["Happy to help!", "Any time!", "My pleasure"]
        },
        {"tag": "hours",
         "patterns": ["What hours is EE office open?", "What are working hours of the department office?", "When does department office open?"],
         "responses": ["The department office is open for 10am-5pm on weekdays.", "Working hours for the EE office are 10am-5pm every weekday"]
        },
        {"tag": "help",
         "patterns": ["Who can I get help?", "Whom should I contact for english learning?", "Who can fix my english pronunciation problems?", "My english is not working, who can fix it?"],
         "responses": ["Let's try it now"]
        },
        {"tag": "study",
         "patterns": ["study","I want to study english","I want to study","How can I start?", "What is study button?", "How to start this learning?" ],
         "responses": ["I have a dream that one day down in Alabama, with its vicious racists, with its governor having his lips dripping with the words of interposition and nullification: one day right there in Alabama little black boys and black girls will be able to join hands with little white boys and white girls as sisters and brothers."]
        },
        {"tag": "opentoday",
         "patterns": ["Is the Deparment office open today?", "When does the Department office open today?", "What are working hours of EE office today?"],
         "responses": ["The department office is open for 10am-5pm on weekdays.", "Working hours for the EE office are 10am-5pm every weekday"]
        },
        {"tag": "name",
         "patterns": ["What is your name?", "What's your name?","Your name?", "Can I get your name?", "Can you tell me your name?", "I want to know your name.","Tell me about yourself" ],
         "responses": ["My name is Sophie"]
        },
        {"tag": "officePhone",
         "patterns": ["What is the contact number of Department office?", "What is the phone number of EE Office?"],
         "responses": ["You can call at #XXXX# to reach the EE office"]
        }
   ]
}

